[
  {
    "py/object": "model.contacts.Contact",
    "firstname": "",
    "middlename": "",
    "lastname": "",
    "nickname": "",
    "address": "",
    "homephone": "",
    "mobile": "",
    "fax": "",
    "work": "",
    "mail": "",
    "mail2": null,
    "mail3": null,
    "bday": "",
    "bmounth": "",
    "byear": "",
    "id": null,
    "all_phones_from_home_page": null
  },
  {
    "py/object": "model.contacts.Contact",
    "firstname": "firstnameMaPf5;Up",
    "middlename": "middlenameB]t",
    "lastname": "lastname+YFN8>|tS",
    "nickname": null,
    "address": "addressr&=eKY",
    "homephone": "homephone",
    "mobile": "mobile P",
    "fax": "fax13 m",
    "work": "workY<",
    "mail": "maillJLDEh",
    "mail2": null,
    "mail3": null,
    "bday": null,
    "bmounth": null,
    "byear": null,
    "id": null,
    "all_phones_from_home_page": null
  },
  {
    "py/object": "model.contacts.Contact",
    "firstname": "firstname",
    "middlename": "middlename q-m S",
    "lastname": "lastname#ir&c .6:n?",
    "nickname": null,
    "address": "addressX Y&bzvb",
    "homephone": "homephoneI",
    "mobile": "mobile +6Gff<jK",
    "fax": "faxL1",
    "work": "workJm$X5 O",
    "mail": "mailtcW8O~*DsZ;",
    "mail2": null,
    "mail3": null,
    "bday": null,
    "bmounth": null,
    "byear": null,
    "id": null,
    "all_phones_from_home_page": null
  },
  {
    "py/object": "model.contacts.Contact",
    "firstname": "firstname M9U",
    "middlename": "middlenameU/V",
    "lastname": "lastnamet Lb:9 K!fs:r",
    "nickname": null,
    "address": "address7$(l5nx",
    "homephone": "homephone",
    "mobile": "mobileGW",
    "fax": "faxA<S;9",
    "work": "workgy%5][",
    "mail": "mailK%nGyja)I{B)=",
    "mail2": null,
    "mail3": null,
    "bday": null,
    "bmounth": null,
    "byear": null,
    "id": null,
    "all_phones_from_home_page": null
  }
]